gsuite_meld/__init__.py
gsuite_meld/document.py
gsuite_meld/drive.py
gsuite_meld/gsuite.py
gsuite_meld/sheet.py
gsuite_meld-0.0.1.dist-info/LICENSE
gsuite_meld-0.0.1.dist-info/METADATA
gsuite_meld-0.0.1.dist-info/WHEEL
gsuite_meld-0.0.1.dist-info/top_level.txt
gsuite_meld-0.0.1.dist-info/RECORD
