Metadata-Version: 2.1
Name: gsuite-meld
Version: 0.0.1
Summary: 'gsuite-meld' is a Python package unifying various GSuite services. It enables easy interaction with Google Sheets, Docs, Drive, and more. Designed for extensibility, it accommodates future GSuite additions, making multi-service workflows simple.
Home-page: https://github.com/loudpumpkins/gsuite-meld
Author: Alexei Panov
Author-email: alexei_panov@hotmail.com
License: MIT
Classifier: License :: OSI Approved :: Apache Software License
Classifier: Programming Language :: Python :: 3.6
Classifier: Operating System :: OS Independent
Requires-Python: >=3.6
License-File: LICENSE
Requires-Dist: google-api-python-client (>=2.92.0)
Requires-Dist: google-auth-httplib2 (>=0.1.0)
Requires-Dist: google-auth-oauthlib (>=1.0.0)
Requires-Dist: typing-extensions (>=4.7.1)
Provides-Extra: dev
Requires-Dist: pytest (>=7.0) ; extra == 'dev'
Requires-Dist: twine (>=4.0.2) ; extra == 'dev'
